{
  "blockchain_explorers": {
    "title": "Blockchain Explorers",
    "theme": {
      "breadcrumb": false,
      "footer": true,
      "sidebar": true,
      "toc": true,
      "pagination": false,
      "layout": "default",
      "typesetting": "default"
    }
  },
  "on_chain_dashboards": {
    "title": "On-Chain Dashboards",
    "theme": {
      "breadcrumb": false,
      "footer": true,
      "sidebar": true,
      "toc": true,
      "pagination": false,
      "layout": "default",
      "typesetting": "default"
    }
  },
  "network_activity": {
    "title": "Network Activity",
    "theme": {
      "breadcrumb": false,
      "footer": true,
      "sidebar": true,
      "toc": true,
      "pagination": false,
      "layout": "default",
      "typesetting": "default"
    }
  },
  "decentralization_metrics": {
    "title": "Decentralization Metrics",
    "theme": {
      "breadcrumb": false,
      "footer": true,
      "sidebar": true,
      "toc": true,
      "pagination": false,
      "layout": "default",
      "typesetting": "default"
    }
  },
  "tokenomics_and_distribution": {
    "title": "Tokenomics and Distribution",
    "theme": {
      "breadcrumb": false,
      "footer": true,
      "sidebar": true,
      "toc": true,
      "pagination": false,
      "layout": "default",
      "typesetting": "default"
    }
  },
  "monetary_policy": {
    "title": "Monetary Policy",
    "theme": {
      "breadcrumb": false,
      "footer": true,
      "sidebar": true,
      "toc": true,
      "pagination": false,
      "layout": "default",
      "typesetting": "default"
    }
  },
  "circulating_supply": {
    "title": "Circulating Supply",
    "theme": {
      "breadcrumb": false,
      "footer": true,
      "sidebar": true,
      "toc": true,
      "pagination": false,
      "layout": "default",
      "typesetting": "default"
    }
  },
  "treasury": {
    "title": "Treasury",
    "theme": {
      "breadcrumb": false,
      "footer": true,
      "sidebar": true,
      "toc": true,
      "pagination": false,
      "layout": "default",
      "typesetting": "default"
    }
  },
  "total_value_locked": {
    "title": "Total Value Locked",
    "theme": {
      "breadcrumb": false,
      "footer": true,
      "sidebar": true,
      "toc": true,
      "pagination": false,
      "layout": "default",
      "typesetting": "default"
    }
  },
  "staking_metrics": {
    "title": "Staking Metrics",
    "theme": {
      "breadcrumb": false,
      "footer": true,
      "sidebar": true,
      "toc": true,
      "pagination": false,
      "layout": "default",
      "typesetting": "default"
    }
  },
  "other_cardano_metrics": {
    "title": "Other Cardano Metrics",
    "theme": {
      "breadcrumb": false,
      "footer": true,
      "sidebar": true,
      "toc": true,
      "pagination": false,
      "layout": "default",
      "typesetting": "default"
    }
  }
}
